{
    "root": "./src",
    "language": "zh-hans",
    "plugins": [
        "sitemap",
        "page-treeview",
        "@honkit/honkit-plugin-ga",
        "@dogatana/page-toc-button",
        "@dogatana/back-to-top-button"
    ],
    "pluginsConfig": {
        "sitemap": {
            "url": "https://play4fun.friesi23.cn/",
            "pathSuffix": "/rfc4918-cn/"
        },
        "page-treeview": {
            "copyright": "",
            "style": "markdown",
            "minHeaderCount": "2",
            "minHeaderDeep": "2",
            "collapsed": true
        },
        "ga": {
            "trackingID": "G-86FL9YRD0F",
            "anonymizeIP": true
        }
    }
}